pykiwoom/__init__.py
pykiwoom/kiwoom.py
pykiwoom/kiwoom_proxy.py
pykiwoom/manager.py
pykiwoom/parser.py
pykiwoom/update.py
pykiwoom-0.1.6.dist-info/LICENSE
pykiwoom-0.1.6.dist-info/METADATA
pykiwoom-0.1.6.dist-info/WHEEL
pykiwoom-0.1.6.dist-info/top_level.txt
pykiwoom-0.1.6.dist-info/RECORD
